JBPhD-2.3.2.data/data/LICENSE.txt
JBPhD-2.3.2.data/data/MANIFEST.in
JBPhD-2.3.2.data/data/README.txt
Task/BL.PNG
Task/BR.PNG
Task/Back_Left.PNG
Task/Back_Right.PNG
Task/Consent Form.docx
Task/Consent.py
Task/Dependencies.py
Task/Dependency Installation.py
Task/Export.py
Task/FL.PNG
Task/FR.PNG
Task/Front_Left.PNG
Task/Front_Right.PNG
Task/ImageSample.PNG
Task/Inverse_Back_Left.PNG
Task/Inverse_Back_Right.PNG
Task/Inverse_Front_Left.PNG
Task/Inverse_Front_Right.PNG
Task/Location.py
Task/MANIFEST.in.txt
Task/Manikin Back Down Left.png
Task/Manikin Back Up Right.png
Task/Manikin front Down Right.png
Task/Manikin front Up Right.png
Task/N-Back count.txt
Task/N-Back.py
Task/PIS.docx
Task/PIS.txt
Task/Python Install.bat
Task/README.txt.txt
Task/RT count.txt
Task/Reaction Time Task - Copy.py
Task/Suffix.bat
Task/Switch count.txt
Task/Switching.py
Task/Task.py
Task/Trial.py
Task/UBL.PNG
Task/UBR.PNG
Task/UFL.PNG
Task/UFR.PNG
Task/asterisk.png
Task/circle.jpg
Task/gdap.json
Task/greentick.png
Task/pins.csv
Task/redcross.png
Task/reddot.png
Task/setup.py
Task/spwf.py
Task/spwfoutput.txt
Task/spwfvalue.txt
Task/suffix.txt
Task/trial.jpeg
Task/uop.ico
Task/uop.jpeg
Task/uop.png
Task/__pycache__/Dependencies.cpython-311.pyc
Task/__pycache__/Export.cpython-311.pyc
Task/__pycache__/Location.cpython-311.pyc
Task/__pycache__/Task.cpython-311.pyc
Task/__pycache__/spwf.cpython-310.pyc
Task/__pycache__/spwf.cpython-311.pyc
JBPhD-2.3.2.dist-info/LICENSE.txt
JBPhD-2.3.2.dist-info/METADATA
JBPhD-2.3.2.dist-info/WHEEL
JBPhD-2.3.2.dist-info/entry_points.txt
JBPhD-2.3.2.dist-info/top_level.txt
JBPhD-2.3.2.dist-info/RECORD
