Metadata-Version: 2.1
Name: JBPhD
Version: 2.3.2
Summary: JB PhD task, for the first of three PhD tasks
Classifier: Programming Language :: Python :: 3
Classifier: License :: OSI Approved
Classifier: Operating System :: OS Independent
License-File: LICENSE.txt
Requires-Dist: sendgrid
Requires-Dist: plyer
Requires-Dist: pygame
Requires-Dist: pandas
Requires-Dist: google-auth
Requires-Dist: google-auth-oauthlib
Requires-Dist: google-auth-httplib2
Requires-Dist: google-api-python-client
Requires-Dist: Pillow
Requires-Dist: Scipy
Requires-Dist: Numpy
